setup.cfg
setup.py
ExoSOFTmodel/__init__.py
ExoSOFTmodel/constants.py
ExoSOFTmodel/cytools.c
ExoSOFTmodel/cytools.pyx
ExoSOFTmodel/cytools.so
ExoSOFTmodel/model.py
ExoSOFTmodel/priors.py
ExoSOFTmodel/setup.py
ExoSOFTmodel/tools.py
ExoSOFTmodel.egg-info/PKG-INFO
ExoSOFTmodel.egg-info/SOURCES.txt
ExoSOFTmodel.egg-info/dependency_links.txt
ExoSOFTmodel.egg-info/requires.txt
ExoSOFTmodel.egg-info/top_level.txt