Metadata-Version: 1.1
Name: ExoSOFTmodel
Version: 1.1.4
Summary: An astronomical model for calculating the predicted astrometry and radial velocity due to a companion.
Home-page: https://github.com/kylemede/ExoSOFTmodel
Author: Kyle Mede
Author-email: kylemede@gmail.com
License: ['GNU GPLv3']
Keywords: model
Platform: UNKNOWN
Classifier: Development Status :: 5 - Production/Stable
Classifier: Intended Audience :: Science/Research
Classifier: Topic :: Scientific/Engineering
Classifier: Programming Language :: Python
